curseforge/__init__.py
curseforge/__main__.py
curseforge/base.py
curseforge/classes/__init__.py
curseforge/classes/base.py
curseforge/classes/cursecategory.py
curseforge/classes/cursegame.py
curseforge/classes/curseimage.py
curseforge/classes/cursemod.py
curseforge/classes/hashe.py
curseforge/classes/manifest.py
curseforge/util/__init__.py
curseforge/util/manifest_parser.py
curseforge/util/probe_cursecache.py
curseforge-1.6.1.dist-info/LICENSE.txt
curseforge-1.6.1.dist-info/METADATA
curseforge-1.6.1.dist-info/WHEEL
curseforge-1.6.1.dist-info/top_level.txt
curseforge-1.6.1.dist-info/RECORD
