Metadata-Version: 2.1
Name: curseforge
Version: 1.6.1
Summary: A no-compromises wrapper for the CurseForge API
Home-page: https://github.com/Advik-B/curseforge-api
Author: Advik
Author-email: <advik.b@gmail.com>
Keywords: CMPDL,Minecraft,Curseforge,API,Wrapper
Classifier: Intended Audience :: Developers
Classifier: Programming Language :: Python :: 3
Classifier: License :: OSI Approved :: MIT License
Classifier: Operating System :: OS Independent
License-File: LICENSE.txt
Requires-Dist: requests
Requires-Dist: diskcache
